calcar/__init__.py
calctp/__init__.py
calcar-0.1.dist-info/LICENCE.txt
calcar-0.1.dist-info/METADATA
calcar-0.1.dist-info/WHEEL
calcar-0.1.dist-info/top_level.txt
calcar-0.1.dist-info/RECORD
